[{"myEnemyCountPairs":[{"myNumEnemies":5,"myEnemy":{"myRoutes":[{"myPoints":[{"myVisibility":true,"myPoint":{"x":824.0,"y":172.0,"hash":0}},{"myVisibility":true,"myPoint":{"x":69.0,"y":173.0,"hash":0}}]},{"myPoints":[{"myVisibility":true,"myPoint":{"x":824.0,"y":172.0,"hash":0}},{"myVisibility":true,"myPoint":{"x":99.0,"y":324.0,"hash":0}}]},{"myPoints":[{"myVisibility":true,"myPoint":{"x":824.0,"y":172.0,"hash":0}},{"myVisibility":true,"myPoint":{"x":76.0,"y":487.0,"hash":0}}]},{"myPoints":[{"myVisibility":true,"myPoint":{"x":760.0,"y":340.0,"hash":0}},{"myVisibility":true,"myPoint":{"x":69.0,"y":173.0,"hash":0}}]},{"myPoints":[{"myVisibility":true,"myPoint":{"x":760.0,"y":340.0,"hash":0}},{"myVisibility":true,"myPoint":{"x":99.0,"y":324.0,"hash":0}}]},{"myPoints":[{"myVisibility":true,"myPoint":{"x":760.0,"y":340.0,"hash":0}},{"myVisibility":true,"myPoint":{"x":76.0,"y":487.0,"hash":0}}]},{"myPoints":[{"myVisibility":true,"myPoint":{"x":824.0,"y":514.0,"hash":0}},{"myVisibility":true,"myPoint":{"x":69.0,"y":173.0,"hash":0}}]},{"myPoints":[{"myVisibility":true,"myPoint":{"x":824.0,"y":514.0,"hash":0}},{"myVisibility":true,"myPoint":{"x":99.0,"y":324.0,"hash":0}}]},{"myPoints":[{"myVisibility":true,"myPoint":{"x":824.0,"y":514.0,"hash":0}},{"myVisibility":true,"myPoint":{"x":76.0,"y":487.0,"hash":0}}]}],"myDamage":5,"myStart":{"myVisibility":true,"myPoint":{"x":824.0,"y":514.0,"hash":0}},"myGoal":{"myVisibility":true,"myPoint":{"x":69.0,"y":173.0,"hash":0}},"myBehaviors":{"defend":{"type":"SimpleDefense","properties":{"myList":[2.9903846153846154],"myHealth":2.9903846153846154,"myInitialHealth":2.9903846153846154}},"movement":{"type":"AIMovement","properties":{"myList":[3.3],"myRoute":[{"myVisibility":true,"myPoint":{"x":824.0,"y":514.0,"hash":0}},{"myVisibility":true,"myPoint":{"x":69.0,"y":173.0,"hash":0}}],"mySpeed":3.3,"myRemainingDistance":828.4358756113837,"myIndex":-1}}},"myName":"Alien1","myRange":4.861111111111112,"myBounty":4,"myImagePath":"./SinglePlayerGames/SpaceDemo/enemyImages/enemy1.png","myIsRemovable":false,"myDebuffs":{},"myDebuffsToRemove":[],"changed":false,"obs":[]}},{"myNumEnemies":5,"myEnemy":{"myRoutes":[{"myPoints":[{"myVisibility":true,"myPoint":{"x":824.0,"y":172.0,"hash":0}},{"myVisibility":true,"myPoint":{"x":69.0,"y":173.0,"hash":0}}]},{"myPoints":[{"myVisibility":true,"myPoint":{"x":824.0,"y":172.0,"hash":0}},{"myVisibility":true,"myPoint":{"x":99.0,"y":324.0,"hash":0}}]},{"myPoints":[{"myVisibility":true,"myPoint":{"x":824.0,"y":172.0,"hash":0}},{"myVisibility":true,"myPoint":{"x":76.0,"y":487.0,"hash":0}}]},{"myPoints":[{"myVisibility":true,"myPoint":{"x":760.0,"y":340.0,"hash":0}},{"myVisibility":true,"myPoint":{"x":69.0,"y":173.0,"hash":0}}]},{"myPoints":[{"myVisibility":true,"myPoint":{"x":760.0,"y":340.0,"hash":0}},{"myVisibility":true,"myPoint":{"x":99.0,"y":324.0,"hash":0}}]},{"myPoints":[{"myVisibility":true,"myPoint":{"x":760.0,"y":340.0,"hash":0}},{"myVisibility":true,"myPoint":{"x":76.0,"y":487.0,"hash":0}}]},{"myPoints":[{"myVisibility":true,"myPoint":{"x":824.0,"y":514.0,"hash":0}},{"myVisibility":true,"myPoint":{"x":69.0,"y":173.0,"hash":0}}]},{"myPoints":[{"myVisibility":true,"myPoint":{"x":824.0,"y":514.0,"hash":0}},{"myVisibility":true,"myPoint":{"x":99.0,"y":324.0,"hash":0}}]},{"myPoints":[{"myVisibility":true,"myPoint":{"x":824.0,"y":514.0,"hash":0}},{"myVisibility":true,"myPoint":{"x":76.0,"y":487.0,"hash":0}}]}],"myDamage":5,"myStart":{"myVisibility":true,"myPoint":{"x":760.0,"y":340.0,"hash":0}},"myGoal":{"myVisibility":true,"myPoint":{"x":76.0,"y":487.0,"hash":0}},"myBehaviors":{"defend":{"type":"SimpleDefense","properties":{"myList":[2.9903846153846154],"myHealth":2.9903846153846154,"myInitialHealth":2.9903846153846154}},"movement":{"type":"AIMovement","properties":{"myList":[3],"myRoute":[{"myVisibility":true,"myPoint":{"x":760.0,"y":340.0,"hash":0}},{"myVisibility":true,"myPoint":{"x":76.0,"y":487.0,"hash":0}}],"mySpeed":3,"myRemainingDistance":699.6177527764715,"myIndex":-1}}},"myName":"Alien2","myRange":4.861111111111112,"myBounty":4,"myImagePath":"./SinglePlayerGames/SpaceDemo/enemyImages/enemy3.png","myIsRemovable":false,"myDebuffs":{},"myDebuffsToRemove":[],"changed":false,"obs":[]}}],"myDurationSeconds":15},{"myEnemyCountPairs":[{"myNumEnemies":10,"myEnemy":{"myRoutes":[{"myPoints":[{"myVisibility":true,"myPoint":{"x":824.0,"y":172.0,"hash":0}},{"myVisibility":true,"myPoint":{"x":69.0,"y":173.0,"hash":0}}]},{"myPoints":[{"myVisibility":true,"myPoint":{"x":824.0,"y":172.0,"hash":0}},{"myVisibility":true,"myPoint":{"x":99.0,"y":324.0,"hash":0}}]},{"myPoints":[{"myVisibility":true,"myPoint":{"x":824.0,"y":172.0,"hash":0}},{"myVisibility":true,"myPoint":{"x":76.0,"y":487.0,"hash":0}}]},{"myPoints":[{"myVisibility":true,"myPoint":{"x":760.0,"y":340.0,"hash":0}},{"myVisibility":true,"myPoint":{"x":69.0,"y":173.0,"hash":0}}]},{"myPoints":[{"myVisibility":true,"myPoint":{"x":760.0,"y":340.0,"hash":0}},{"myVisibility":true,"myPoint":{"x":99.0,"y":324.0,"hash":0}}]},{"myPoints":[{"myVisibility":true,"myPoint":{"x":760.0,"y":340.0,"hash":0}},{"myVisibility":true,"myPoint":{"x":76.0,"y":487.0,"hash":0}}]},{"myPoints":[{"myVisibility":true,"myPoint":{"x":824.0,"y":514.0,"hash":0}},{"myVisibility":true,"myPoint":{"x":69.0,"y":173.0,"hash":0}}]},{"myPoints":[{"myVisibility":true,"myPoint":{"x":824.0,"y":514.0,"hash":0}},{"myVisibility":true,"myPoint":{"x":99.0,"y":324.0,"hash":0}}]},{"myPoints":[{"myVisibility":true,"myPoint":{"x":824.0,"y":514.0,"hash":0}},{"myVisibility":true,"myPoint":{"x":76.0,"y":487.0,"hash":0}}]}],"myDamage":5,"myStart":{"myVisibility":true,"myPoint":{"x":824.0,"y":514.0,"hash":0}},"myGoal":{"myVisibility":true,"myPoint":{"x":69.0,"y":173.0,"hash":0}},"myBehaviors":{"defend":{"type":"SimpleDefense","properties":{"myList":[2.9903846153846154],"myHealth":2.9903846153846154,"myInitialHealth":2.9903846153846154}},"movement":{"type":"AIMovement","properties":{"myList":[3.3],"myRoute":[{"myVisibility":true,"myPoint":{"x":824.0,"y":514.0,"hash":0}},{"myVisibility":true,"myPoint":{"x":69.0,"y":173.0,"hash":0}}],"mySpeed":3.3,"myRemainingDistance":828.4358756113837,"myIndex":-1}}},"myName":"Alien1","myRange":4.861111111111112,"myBounty":4,"myImagePath":"./SinglePlayerGames/SpaceDemo/enemyImages/enemy1.png","myIsRemovable":false,"myDebuffs":{},"myDebuffsToRemove":[],"changed":false,"obs":[]}},{"myNumEnemies":5,"myEnemy":{"myRoutes":[{"myPoints":[{"myVisibility":true,"myPoint":{"x":824.0,"y":172.0,"hash":0}},{"myVisibility":true,"myPoint":{"x":69.0,"y":173.0,"hash":0}}]},{"myPoints":[{"myVisibility":true,"myPoint":{"x":824.0,"y":172.0,"hash":0}},{"myVisibility":true,"myPoint":{"x":99.0,"y":324.0,"hash":0}}]},{"myPoints":[{"myVisibility":true,"myPoint":{"x":824.0,"y":172.0,"hash":0}},{"myVisibility":true,"myPoint":{"x":76.0,"y":487.0,"hash":0}}]},{"myPoints":[{"myVisibility":true,"myPoint":{"x":760.0,"y":340.0,"hash":0}},{"myVisibility":true,"myPoint":{"x":69.0,"y":173.0,"hash":0}}]},{"myPoints":[{"myVisibility":true,"myPoint":{"x":760.0,"y":340.0,"hash":0}},{"myVisibility":true,"myPoint":{"x":99.0,"y":324.0,"hash":0}}]},{"myPoints":[{"myVisibility":true,"myPoint":{"x":760.0,"y":340.0,"hash":0}},{"myVisibility":true,"myPoint":{"x":76.0,"y":487.0,"hash":0}}]},{"myPoints":[{"myVisibility":true,"myPoint":{"x":824.0,"y":514.0,"hash":0}},{"myVisibility":true,"myPoint":{"x":69.0,"y":173.0,"hash":0}}]},{"myPoints":[{"myVisibility":true,"myPoint":{"x":824.0,"y":514.0,"hash":0}},{"myVisibility":true,"myPoint":{"x":99.0,"y":324.0,"hash":0}}]},{"myPoints":[{"myVisibility":true,"myPoint":{"x":824.0,"y":514.0,"hash":0}},{"myVisibility":true,"myPoint":{"x":76.0,"y":487.0,"hash":0}}]}],"myDamage":5,"myStart":{"myVisibility":true,"myPoint":{"x":760.0,"y":340.0,"hash":0}},"myGoal":{"myVisibility":true,"myPoint":{"x":76.0,"y":487.0,"hash":0}},"myBehaviors":{"defend":{"type":"SimpleDefense","properties":{"myList":[2.9903846153846154],"myHealth":2.9903846153846154,"myInitialHealth":2.9903846153846154}},"movement":{"type":"AIMovement","properties":{"myList":[3],"myRoute":[{"myVisibility":true,"myPoint":{"x":760.0,"y":340.0,"hash":0}},{"myVisibility":true,"myPoint":{"x":76.0,"y":487.0,"hash":0}}],"mySpeed":3,"myRemainingDistance":699.6177527764715,"myIndex":-1}}},"myName":"Alien2","myRange":4.861111111111112,"myBounty":4,"myImagePath":"./SinglePlayerGames/SpaceDemo/enemyImages/enemy3.png","myIsRemovable":false,"myDebuffs":{},"myDebuffsToRemove":[],"changed":false,"obs":[]}}],"myDurationSeconds":20},{"myEnemyCountPairs":[{"myNumEnemies":10,"myEnemy":{"myRoutes":[{"myPoints":[{"myVisibility":true,"myPoint":{"x":824.0,"y":172.0,"hash":0}},{"myVisibility":true,"myPoint":{"x":69.0,"y":173.0,"hash":0}}]},{"myPoints":[{"myVisibility":true,"myPoint":{"x":824.0,"y":172.0,"hash":0}},{"myVisibility":true,"myPoint":{"x":99.0,"y":324.0,"hash":0}}]},{"myPoints":[{"myVisibility":true,"myPoint":{"x":824.0,"y":172.0,"hash":0}},{"myVisibility":true,"myPoint":{"x":76.0,"y":487.0,"hash":0}}]},{"myPoints":[{"myVisibility":true,"myPoint":{"x":760.0,"y":340.0,"hash":0}},{"myVisibility":true,"myPoint":{"x":69.0,"y":173.0,"hash":0}}]},{"myPoints":[{"myVisibility":true,"myPoint":{"x":760.0,"y":340.0,"hash":0}},{"myVisibility":true,"myPoint":{"x":99.0,"y":324.0,"hash":0}}]},{"myPoints":[{"myVisibility":true,"myPoint":{"x":760.0,"y":340.0,"hash":0}},{"myVisibility":true,"myPoint":{"x":76.0,"y":487.0,"hash":0}}]},{"myPoints":[{"myVisibility":true,"myPoint":{"x":824.0,"y":514.0,"hash":0}},{"myVisibility":true,"myPoint":{"x":69.0,"y":173.0,"hash":0}}]},{"myPoints":[{"myVisibility":true,"myPoint":{"x":824.0,"y":514.0,"hash":0}},{"myVisibility":true,"myPoint":{"x":99.0,"y":324.0,"hash":0}}]},{"myPoints":[{"myVisibility":true,"myPoint":{"x":824.0,"y":514.0,"hash":0}},{"myVisibility":true,"myPoint":{"x":76.0,"y":487.0,"hash":0}}]}],"myDamage":5,"myStart":{"myVisibility":true,"myPoint":{"x":824.0,"y":514.0,"hash":0}},"myGoal":{"myVisibility":true,"myPoint":{"x":69.0,"y":173.0,"hash":0}},"myBehaviors":{"defend":{"type":"SimpleDefense","properties":{"myList":[2.9903846153846154],"myHealth":2.9903846153846154,"myInitialHealth":2.9903846153846154}},"movement":{"type":"AIMovement","properties":{"myList":[3.3],"myRoute":[{"myVisibility":true,"myPoint":{"x":824.0,"y":514.0,"hash":0}},{"myVisibility":true,"myPoint":{"x":69.0,"y":173.0,"hash":0}}],"mySpeed":3.3,"myRemainingDistance":828.4358756113837,"myIndex":-1}}},"myName":"Alien1","myRange":4.861111111111112,"myBounty":4,"myImagePath":"./SinglePlayerGames/SpaceDemo/enemyImages/enemy1.png","myIsRemovable":false,"myDebuffs":{},"myDebuffsToRemove":[],"changed":false,"obs":[]}},{"myNumEnemies":10,"myEnemy":{"myRoutes":[{"myPoints":[{"myVisibility":true,"myPoint":{"x":824.0,"y":172.0,"hash":0}},{"myVisibility":true,"myPoint":{"x":69.0,"y":173.0,"hash":0}}]},{"myPoints":[{"myVisibility":true,"myPoint":{"x":824.0,"y":172.0,"hash":0}},{"myVisibility":true,"myPoint":{"x":99.0,"y":324.0,"hash":0}}]},{"myPoints":[{"myVisibility":true,"myPoint":{"x":824.0,"y":172.0,"hash":0}},{"myVisibility":true,"myPoint":{"x":76.0,"y":487.0,"hash":0}}]},{"myPoints":[{"myVisibility":true,"myPoint":{"x":760.0,"y":340.0,"hash":0}},{"myVisibility":true,"myPoint":{"x":69.0,"y":173.0,"hash":0}}]},{"myPoints":[{"myVisibility":true,"myPoint":{"x":760.0,"y":340.0,"hash":0}},{"myVisibility":true,"myPoint":{"x":99.0,"y":324.0,"hash":0}}]},{"myPoints":[{"myVisibility":true,"myPoint":{"x":760.0,"y":340.0,"hash":0}},{"myVisibility":true,"myPoint":{"x":76.0,"y":487.0,"hash":0}}]},{"myPoints":[{"myVisibility":true,"myPoint":{"x":824.0,"y":514.0,"hash":0}},{"myVisibility":true,"myPoint":{"x":69.0,"y":173.0,"hash":0}}]},{"myPoints":[{"myVisibility":true,"myPoint":{"x":824.0,"y":514.0,"hash":0}},{"myVisibility":true,"myPoint":{"x":99.0,"y":324.0,"hash":0}}]},{"myPoints":[{"myVisibility":true,"myPoint":{"x":824.0,"y":514.0,"hash":0}},{"myVisibility":true,"myPoint":{"x":76.0,"y":487.0,"hash":0}}]}],"myDamage":5,"myStart":{"myVisibility":true,"myPoint":{"x":760.0,"y":340.0,"hash":0}},"myGoal":{"myVisibility":true,"myPoint":{"x":76.0,"y":487.0,"hash":0}},"myBehaviors":{"defend":{"type":"SimpleDefense","properties":{"myList":[2.9903846153846154],"myHealth":2.9903846153846154,"myInitialHealth":2.9903846153846154}},"movement":{"type":"AIMovement","properties":{"myList":[3],"myRoute":[{"myVisibility":true,"myPoint":{"x":760.0,"y":340.0,"hash":0}},{"myVisibility":true,"myPoint":{"x":76.0,"y":487.0,"hash":0}}],"mySpeed":3,"myRemainingDistance":699.6177527764715,"myIndex":-1}}},"myName":"Alien2","myRange":4.861111111111112,"myBounty":4,"myImagePath":"./SinglePlayerGames/SpaceDemo/enemyImages/enemy3.png","myIsRemovable":false,"myDebuffs":{},"myDebuffsToRemove":[],"changed":false,"obs":[]}}],"myDurationSeconds":20},{"myEnemyCountPairs":[{"myNumEnemies":15,"myEnemy":{"myRoutes":[{"myPoints":[{"myVisibility":true,"myPoint":{"x":824.0,"y":172.0,"hash":0}},{"myVisibility":true,"myPoint":{"x":69.0,"y":173.0,"hash":0}}]},{"myPoints":[{"myVisibility":true,"myPoint":{"x":824.0,"y":172.0,"hash":0}},{"myVisibility":true,"myPoint":{"x":99.0,"y":324.0,"hash":0}}]},{"myPoints":[{"myVisibility":true,"myPoint":{"x":824.0,"y":172.0,"hash":0}},{"myVisibility":true,"myPoint":{"x":76.0,"y":487.0,"hash":0}}]},{"myPoints":[{"myVisibility":true,"myPoint":{"x":760.0,"y":340.0,"hash":0}},{"myVisibility":true,"myPoint":{"x":69.0,"y":173.0,"hash":0}}]},{"myPoints":[{"myVisibility":true,"myPoint":{"x":760.0,"y":340.0,"hash":0}},{"myVisibility":true,"myPoint":{"x":99.0,"y":324.0,"hash":0}}]},{"myPoints":[{"myVisibility":true,"myPoint":{"x":760.0,"y":340.0,"hash":0}},{"myVisibility":true,"myPoint":{"x":76.0,"y":487.0,"hash":0}}]},{"myPoints":[{"myVisibility":true,"myPoint":{"x":824.0,"y":514.0,"hash":0}},{"myVisibility":true,"myPoint":{"x":69.0,"y":173.0,"hash":0}}]},{"myPoints":[{"myVisibility":true,"myPoint":{"x":824.0,"y":514.0,"hash":0}},{"myVisibility":true,"myPoint":{"x":99.0,"y":324.0,"hash":0}}]},{"myPoints":[{"myVisibility":true,"myPoint":{"x":824.0,"y":514.0,"hash":0}},{"myVisibility":true,"myPoint":{"x":76.0,"y":487.0,"hash":0}}]}],"myDamage":5,"myStart":{"myVisibility":true,"myPoint":{"x":824.0,"y":514.0,"hash":0}},"myGoal":{"myVisibility":true,"myPoint":{"x":69.0,"y":173.0,"hash":0}},"myBehaviors":{"defend":{"type":"SimpleDefense","properties":{"myList":[2.9903846153846154],"myHealth":2.9903846153846154,"myInitialHealth":2.9903846153846154}},"movement":{"type":"AIMovement","properties":{"myList":[3.3],"myRoute":[{"myVisibility":true,"myPoint":{"x":824.0,"y":514.0,"hash":0}},{"myVisibility":true,"myPoint":{"x":69.0,"y":173.0,"hash":0}}],"mySpeed":3.3,"myRemainingDistance":828.4358756113837,"myIndex":-1}}},"myName":"Alien1","myRange":4.861111111111112,"myBounty":4,"myImagePath":"./SinglePlayerGames/SpaceDemo/enemyImages/enemy1.png","myIsRemovable":false,"myDebuffs":{},"myDebuffsToRemove":[],"changed":false,"obs":[]}},{"myNumEnemies":15,"myEnemy":{"myRoutes":[{"myPoints":[{"myVisibility":true,"myPoint":{"x":824.0,"y":172.0,"hash":0}},{"myVisibility":true,"myPoint":{"x":69.0,"y":173.0,"hash":0}}]},{"myPoints":[{"myVisibility":true,"myPoint":{"x":824.0,"y":172.0,"hash":0}},{"myVisibility":true,"myPoint":{"x":99.0,"y":324.0,"hash":0}}]},{"myPoints":[{"myVisibility":true,"myPoint":{"x":824.0,"y":172.0,"hash":0}},{"myVisibility":true,"myPoint":{"x":76.0,"y":487.0,"hash":0}}]},{"myPoints":[{"myVisibility":true,"myPoint":{"x":760.0,"y":340.0,"hash":0}},{"myVisibility":true,"myPoint":{"x":69.0,"y":173.0,"hash":0}}]},{"myPoints":[{"myVisibility":true,"myPoint":{"x":760.0,"y":340.0,"hash":0}},{"myVisibility":true,"myPoint":{"x":99.0,"y":324.0,"hash":0}}]},{"myPoints":[{"myVisibility":true,"myPoint":{"x":760.0,"y":340.0,"hash":0}},{"myVisibility":true,"myPoint":{"x":76.0,"y":487.0,"hash":0}}]},{"myPoints":[{"myVisibility":true,"myPoint":{"x":824.0,"y":514.0,"hash":0}},{"myVisibility":true,"myPoint":{"x":69.0,"y":173.0,"hash":0}}]},{"myPoints":[{"myVisibility":true,"myPoint":{"x":824.0,"y":514.0,"hash":0}},{"myVisibility":true,"myPoint":{"x":99.0,"y":324.0,"hash":0}}]},{"myPoints":[{"myVisibility":true,"myPoint":{"x":824.0,"y":514.0,"hash":0}},{"myVisibility":true,"myPoint":{"x":76.0,"y":487.0,"hash":0}}]}],"myDamage":5,"myStart":{"myVisibility":true,"myPoint":{"x":760.0,"y":340.0,"hash":0}},"myGoal":{"myVisibility":true,"myPoint":{"x":76.0,"y":487.0,"hash":0}},"myBehaviors":{"defend":{"type":"SimpleDefense","properties":{"myList":[2.9903846153846154],"myHealth":2.9903846153846154,"myInitialHealth":2.9903846153846154}},"movement":{"type":"AIMovement","properties":{"myList":[3],"myRoute":[{"myVisibility":true,"myPoint":{"x":760.0,"y":340.0,"hash":0}},{"myVisibility":true,"myPoint":{"x":76.0,"y":487.0,"hash":0}}],"mySpeed":3,"myRemainingDistance":699.6177527764715,"myIndex":-1}}},"myName":"Alien2","myRange":4.861111111111112,"myBounty":4,"myImagePath":"./SinglePlayerGames/SpaceDemo/enemyImages/enemy3.png","myIsRemovable":false,"myDebuffs":{},"myDebuffsToRemove":[],"changed":false,"obs":[]}}],"myDurationSeconds":20},{"myEnemyCountPairs":[{"myNumEnemies":20,"myEnemy":{"myRoutes":[{"myPoints":[{"myVisibility":true,"myPoint":{"x":824.0,"y":172.0,"hash":0}},{"myVisibility":true,"myPoint":{"x":69.0,"y":173.0,"hash":0}}]},{"myPoints":[{"myVisibility":true,"myPoint":{"x":824.0,"y":172.0,"hash":0}},{"myVisibility":true,"myPoint":{"x":99.0,"y":324.0,"hash":0}}]},{"myPoints":[{"myVisibility":true,"myPoint":{"x":824.0,"y":172.0,"hash":0}},{"myVisibility":true,"myPoint":{"x":76.0,"y":487.0,"hash":0}}]},{"myPoints":[{"myVisibility":true,"myPoint":{"x":760.0,"y":340.0,"hash":0}},{"myVisibility":true,"myPoint":{"x":69.0,"y":173.0,"hash":0}}]},{"myPoints":[{"myVisibility":true,"myPoint":{"x":760.0,"y":340.0,"hash":0}},{"myVisibility":true,"myPoint":{"x":99.0,"y":324.0,"hash":0}}]},{"myPoints":[{"myVisibility":true,"myPoint":{"x":760.0,"y":340.0,"hash":0}},{"myVisibility":true,"myPoint":{"x":76.0,"y":487.0,"hash":0}}]},{"myPoints":[{"myVisibility":true,"myPoint":{"x":824.0,"y":514.0,"hash":0}},{"myVisibility":true,"myPoint":{"x":69.0,"y":173.0,"hash":0}}]},{"myPoints":[{"myVisibility":true,"myPoint":{"x":824.0,"y":514.0,"hash":0}},{"myVisibility":true,"myPoint":{"x":99.0,"y":324.0,"hash":0}}]},{"myPoints":[{"myVisibility":true,"myPoint":{"x":824.0,"y":514.0,"hash":0}},{"myVisibility":true,"myPoint":{"x":76.0,"y":487.0,"hash":0}}]}],"myDamage":5,"myStart":{"myVisibility":true,"myPoint":{"x":824.0,"y":514.0,"hash":0}},"myGoal":{"myVisibility":true,"myPoint":{"x":69.0,"y":173.0,"hash":0}},"myBehaviors":{"defend":{"type":"SimpleDefense","properties":{"myList":[2.9903846153846154],"myHealth":2.9903846153846154,"myInitialHealth":2.9903846153846154}},"movement":{"type":"AIMovement","properties":{"myList":[3.3],"myRoute":[{"myVisibility":true,"myPoint":{"x":824.0,"y":514.0,"hash":0}},{"myVisibility":true,"myPoint":{"x":69.0,"y":173.0,"hash":0}}],"mySpeed":3.3,"myRemainingDistance":828.4358756113837,"myIndex":-1}}},"myName":"Alien1","myRange":4.861111111111112,"myBounty":4,"myImagePath":"./SinglePlayerGames/SpaceDemo/enemyImages/enemy1.png","myIsRemovable":false,"myDebuffs":{},"myDebuffsToRemove":[],"changed":false,"obs":[]}},{"myNumEnemies":15,"myEnemy":{"myRoutes":[{"myPoints":[{"myVisibility":true,"myPoint":{"x":824.0,"y":172.0,"hash":0}},{"myVisibility":true,"myPoint":{"x":69.0,"y":173.0,"hash":0}}]},{"myPoints":[{"myVisibility":true,"myPoint":{"x":824.0,"y":172.0,"hash":0}},{"myVisibility":true,"myPoint":{"x":99.0,"y":324.0,"hash":0}}]},{"myPoints":[{"myVisibility":true,"myPoint":{"x":824.0,"y":172.0,"hash":0}},{"myVisibility":true,"myPoint":{"x":76.0,"y":487.0,"hash":0}}]},{"myPoints":[{"myVisibility":true,"myPoint":{"x":760.0,"y":340.0,"hash":0}},{"myVisibility":true,"myPoint":{"x":69.0,"y":173.0,"hash":0}}]},{"myPoints":[{"myVisibility":true,"myPoint":{"x":760.0,"y":340.0,"hash":0}},{"myVisibility":true,"myPoint":{"x":99.0,"y":324.0,"hash":0}}]},{"myPoints":[{"myVisibility":true,"myPoint":{"x":760.0,"y":340.0,"hash":0}},{"myVisibility":true,"myPoint":{"x":76.0,"y":487.0,"hash":0}}]},{"myPoints":[{"myVisibility":true,"myPoint":{"x":824.0,"y":514.0,"hash":0}},{"myVisibility":true,"myPoint":{"x":69.0,"y":173.0,"hash":0}}]},{"myPoints":[{"myVisibility":true,"myPoint":{"x":824.0,"y":514.0,"hash":0}},{"myVisibility":true,"myPoint":{"x":99.0,"y":324.0,"hash":0}}]},{"myPoints":[{"myVisibility":true,"myPoint":{"x":824.0,"y":514.0,"hash":0}},{"myVisibility":true,"myPoint":{"x":76.0,"y":487.0,"hash":0}}]}],"myDamage":5,"myStart":{"myVisibility":true,"myPoint":{"x":760.0,"y":340.0,"hash":0}},"myGoal":{"myVisibility":true,"myPoint":{"x":76.0,"y":487.0,"hash":0}},"myBehaviors":{"defend":{"type":"SimpleDefense","properties":{"myList":[2.9903846153846154],"myHealth":2.9903846153846154,"myInitialHealth":2.9903846153846154}},"movement":{"type":"AIMovement","properties":{"myList":[3],"myRoute":[{"myVisibility":true,"myPoint":{"x":760.0,"y":340.0,"hash":0}},{"myVisibility":true,"myPoint":{"x":76.0,"y":487.0,"hash":0}}],"mySpeed":3,"myRemainingDistance":699.6177527764715,"myIndex":-1}}},"myName":"Alien2","myRange":4.861111111111112,"myBounty":4,"myImagePath":"./SinglePlayerGames/SpaceDemo/enemyImages/enemy3.png","myIsRemovable":false,"myDebuffs":{},"myDebuffsToRemove":[],"changed":false,"obs":[]}}],"myDurationSeconds":20}]